.DS_Store
_auto.py
_docs.py
_gui.py
inits.py
cli_ops/__init__.py
cli_ops/commands.py
common/__init__.py
common/calc_pss.py
common/dialog_app.py
common/exceptions.py
common/file_handler.py
common/fits_file_reader.py
common/fitting.py
common/get_resources.py
common/load_prog.py
common/log_conf.py
common/messaging.py
common/misc_funcs.py
common/plot_manager.py
common/populate_fit_parameters.py
common/process_selection.py
common/quick_reader.py
common/scan_parameters.py
common/sqlite_db.py
gui/__init__.py
gui/canvas_manager.py
gui/edit_driftscan_window.py
gui/edit_timeseries_window.py
gui/edit_timeseries_window2.py
gui/logfile.txt
gui/main_gui_logic.py
gui/main_window.py
gui/secondary_canvas_manager.py
gui/timeseries_canvas.py
gui/view_plots_window.py
predefs/Jupiter_calsky_2007.dat
predefs/Jupiter_calsky_2008.dat
predefs/Jupiter_calsky_2009.dat
predefs/Jupiter_calsky_2010.dat
predefs/Jupiter_calsky_2011.dat
predefs/Jupiter_calsky_2012.dat
predefs/Jupiter_calsky_2013.dat
predefs/Jupiter_calsky_2014.dat
predefs/Jupiter_calsky_2015.dat
predefs/Jupiter_calsky_2016.dat
predefs/Jupiter_calsky_2017.dat
predefs/Jupiter_calsky_2018.dat
predefs/Jupiter_calsky_2019.dat
predefs/Jupiter_calsky_2020.dat
predefs/Jupiter_calsky_2021.dat
predefs/Jupiter_calsky_2022.dat
predefs/Jupiter_calsky_2023.dat
predefs/__init__.py
predefs/cal_names_list.txt
predefs/default_hart_pss.txt
predefs/logbook_entries.txt
predefs/nasa_jpl_results.txt
dran-0.0.44.dist-info/AUTHORS.rst
dran-0.0.44.dist-info/LICENSE
dran-0.0.44.dist-info/METADATA
dran-0.0.44.dist-info/WHEEL
dran-0.0.44.dist-info/entry_points.txt
dran-0.0.44.dist-info/top_level.txt
dran-0.0.44.dist-info/RECORD
