Metadata-Version: 2.1
Name: dran
Version: 0.0.44
Summary: Data reduction and analysis of HartRAO 26m telescope drift scans
Home-page: https://github.com/Pfesi/dran
Author: Pfesesani van Zyl
Author-email: pfesi24@gmail.com
Project-URL: Documentation, https://dran-docs.readthedocs.io/en/latest/
Project-URL: Changelog, https://dran-docs.readthedocs.io/en/latest/extras/changelog.html
Project-URL: Issue Tracker, https://github.com/Pfesi/dran/issues
Keywords: dran,single-dish,hartrao
Classifier: Intended Audience :: End Users/Desktop
Classifier: Development Status :: 4 - Beta
Classifier: Programming Language :: Python :: 3.9
Classifier: Topic :: Scientific/Engineering :: Astronomy
Classifier: Operating System :: OS Independent
Requires-Python: >=3.8
License-File: LICENSE
License-File: AUTHORS.rst
Requires-Dist: astropy ==5.2.2
Requires-Dist: contourpy ==1.1.1
Requires-Dist: cycler ==0.12.1
Requires-Dist: fonttools ==4.46.0
Requires-Dist: importlib-resources ==6.1.1
Requires-Dist: joblib ==1.3.2
Requires-Dist: kiwisolver ==1.4.5
Requires-Dist: matplotlib ==3.7.4
Requires-Dist: numpy ==1.24.4
Requires-Dist: packaging ==23.2
Requires-Dist: pandas ==2.0.3
Requires-Dist: Pillow ==10.1.0
Requires-Dist: pyerfa ==2.0.0.3
Requires-Dist: pyparsing ==3.1.1
Requires-Dist: PyQt5 ==5.12.2
Requires-Dist: PyQt5-Qt5 ==5.12.2
Requires-Dist: PyQt5-sip ==12.13.0
Requires-Dist: python-dateutil ==2.8.2
Requires-Dist: pytz ==2023.3.post1
Requires-Dist: PyYAML ==6.0.1
Requires-Dist: scikit-learn ==1.3.2
Requires-Dist: scipy ==1.10.1
Requires-Dist: six ==1.16.0
Requires-Dist: threadpoolctl ==3.2.0
Requires-Dist: tzdata ==2023.3
Requires-Dist: zipp ==3.17.0
Provides-Extra: dev
Requires-Dist: pytest >=3.7 ; extra == 'dev'
